{
    "language_code": "fr",

    "base_url": "/fr",

    "basetitle": "Bruno Costa - Galerie",

    "meta": {
        "keywords": "Galerie Bruno Costa, Bruno Costa, Galerie, Photographie Bruno Costa, Photographie, Portfolio Bruno Costa, Portfolio",
        "description": "Galerie Bruno Costa",
        "author": "Bruno Costa"
    },

    "languages": [
        {
            "title": "PT",
            "base_url": "/pt"
        },
        {
            "title": "EN",
            "base_url": "/en"
        },
        {
            "title": "FR",
            "base_url": "/fr",
            "is_selected": true
        }
    ],

    "text": {
        "menu": "Menu",
        "selected_works": "Œuvres choisies",
        "location": "Lieu",
        "date": "Date",
        "year": "Année",
        "gear": "Équipement",
        "share": "Partager",
        "all": "Tout",
        "share_on_prefix": "Partager cette page sur ",
        "not_found_title": "404",
        "not_found_line_1": "Il semble que tu as trouvé une page sur laquelle je travaille encore. Je vais essayer de la finir au plus vite.",
        "not_found_line_2": "Pendant ce temps, inspires et, à l'expiration, cliques <a href='/fr/work/well-kept-secret.html'><b>ici</b></a> et contemple un paysage super cool."
    },

    "home": {
        "title": "Page d'accueil"
    },
    "about": {
        "title": "À propos"
    },
    "contact": {
        "title": "Contact",
        "text": {
            "placeholder": "Prendre contact",
            "line_1": "Veux-tu collaborer sur un projet? Juste dire bonjour? Vas-y et envoie-moi quelque chose!",
            "name": "Nom",
            "email": "E-mail",
            "message": "Message",
            "send": "Envoyer"
        }
    },
    "terms_conditions": {
        "title": "Termes et Conditions",
        "text": {
            "line_1": "Toutes les images et vidéos présentées sur ce site sont la propriété de Bruno Costa, sont protégées par le droit d'auteur et ne peuvent en aucun cas être utilisées à des fins personnelles ou commerciales sans accord préalable ou licence. Contacte-moi pour l'autorisation.",
            "line_2": "Tu peux partager des images/vidéos sur les réseaux sociaux personnels, à condition de donner crédit (© Bruno Costa) et identifier (vérifier mes identifiants de réseaux sociaux en bas de page)."
        }
    },
    
    "footer": {
        "policy": "© Bruno Costa 2022",
        "social": {
            "linkedin": {
                "title": "linkedin",
                "url": "https://www.linkedin.com/in/brunorafaelcosta"
            },
            "instagram": {
                "title": "instagram",
                "url": "https://www.instagram.com/brunorafael.costa/"
            }
        }
    },

    "cookie_policy": {
        "title": "Politique de Cookies",
        "consent_modal": {
            "description": "On utilise des cookies, propres et tiers, pour améliorer la navigation sur ce site et analyser et personnaliser son utilisation. Pour plus d'informations, lire notre <a href='/fr/cookie-policy.html' target='_blank'>Politique de Cookies</a>.",
            "accept_all": "Tout autoriser"
        },
        "settings_modal": {
            "title": "Préférences",
            "subtitle": "Utilisation des cookies 📢",
            "description": "En savoir plus sur les types de cookies que nous utilisons et sélectionner ceux auxquels tu consens.",
            "save": "Enregistrer",
            "accept_all": "Tout autoriser",
            "accept_necessary": "Autoriser le nécessaire",
            "close": "Fermer",
            "strictly_necessary_cookies_title": "Cookies essentiels (requis)",
            "strictly_necessary_cookies_description": "Cookies propres et tiers qui garantissent le bon fonctionnement du site.",
            "performance_and_analytics_cookies_title": "Cookies de performance et de personnalisation",
            "performance_and_analytics_cookies_description": "Cookies qui collectent et analysent des informations sur l'utilisation du site, nous permettant d'améliorer et de personnaliser l'expérience de navigation.",
            "more_information_title": "Plus d'information",
            "more_information_description": "Tu peux à tout moment en savoir plus sur les cookies et modifier tes préférences sur la <a href='/fr/cookie-policy.html' target='_blank'>page des cookies</a>."
        },
        "text": {
            "page_last_update": "Dernière mise à jour : janvier 2022",
            "page_what_are_cookies": "Que sont les cookies ?",
            "page_what_are_cookies_line_1": "Les cookies sont de petits fichiers texte uniques qu'un site envoie à ton ordinateur lorsque tu le visites - il peut s'agir de cookies de session qui se terminent lorsque tu fermes ton navigateur ou de cookies persistants qui restent jusqu'à ce que tu les supprimes. Par exemple, nous utilisons un cookie persistant avec ta sélection de langue, tu n'as donc pas à le sélectionner à chaque fois que tu nous rends visite.",
            "page_what_are_cookies_line_2": "Pour plus de détails sur les cookies, tu peux visiter <a href='https://www.aboutcookies.org' target='_blank'>www.aboutcookies.org</a>.",
            "page_how_do_we_use_cookies": "Comment utilisons-nous les cookies ?",
            "page_how_do_we_use_cookies_line_1": "En plus du cookie qui conserve la sélection de la langue, nous utilisons également les services suivants qui, à leur tour, peuvent également utiliser des cookies:",
            "page_how_do_we_use_cookies_google_analytics": "<a href='https://analytics.google.com/' target='_blank'>Google Analytics</a> - Utilisé pour collecter des informations sur la façon dont les utilisateurs naviguent sur notre site. Nous utilisons les informations pour compiler des rapports afin de nous aider à améliorer l'expérience de l'utilisateur.",
            "page_how_do_we_use_cookies_line_2": "Pour plus d'informations, <a href='/fr/contact.html'>prends contact avec nous</a>.",
            "page_cookie_preferences": "Comment peux-tu modifier tes préférences en matière de cookies?",
            "page_cookie_preferences_line_1": "Tu peux autoriser ou refuser les différents cookies à tout moment et selon tes préférences. Pour cela, il te suffit d'accéder à la fenêtre de configuration:"
        }
    },
    
    "works": {
        "beginnings": {
            "title": "Débuts",
            "text": {
                "quote_1": "Dans chaque début habite un enchantement qui nous protège et qui nous aide à vivre.",
                "quote_1_author": "Hermann Hesse, Étapes"
            },
            "details": {
                "location": {
                    "url": "https://www.google.fr/maps/place/Coimbra",
                    "value": "Coimbra, Portugal"
                },
                "date": "27 mai 2019",
                "gear": "Sony A7 + FE 28-70 mm F3.5-5.6 OSS"
            }
        },
        "well-kept-secret": {
            "title": "Secret bien gardé",
            "text": {
                "quote_1_1": "Rien au monde n'a jamais été vu",
                "quote_1_1_translation_source": "Nothing in the world was ever seen",
                "quote_1_2": "Écris-le sur le vent",
                "quote_1_2_translation_source": "Write it on the wind",
                "quote_1_3": "Ce rêve vivant",
                "quote_1_3_translation_source": "This living dream",
                "quote_1_author": "David Gray, Laughing Gas"
            },
            "details": {
                "location": {
                    "url": "https://www.google.fr/maps/place/Tibo,+Arcos+de+Valdevez",
                    "value": "Tibo, Arcos de Valdevez, Portugal"
                },
                "date": "30 juillet 2019",
                "gear": "Sony A7 + FE 28-70 mm F3.5-5.6 OSS"
            }
        },
        "old-fisherman": {
            "title": "Vieux Pêcheur",
            "text": {
                "quote_1": "C'est pas parce que tu crevais de faim que t'as tué ce poisson-là, se dit-il. Ni pour le vendre. Tu l'as tué par orgueil. Tu l'as tué parce que t'es né pêcheur. Ce poisson-là tu l'aimais quand il était en vie, et tu l'as aimé aussi après. Si tu l'aimes, c'est pas un péché de l'avoir tué. Ou c'est-y encore plus mal?",
                "quote_1_author": "Ernest Hemingway, Le Vieil Homme et la Mer"
            },
            "details": {
                "location": {
                    "url": "https://www.google.fr/maps/place/Azenhas+do+Mar,+Colares",
                    "value": "Azenhas do Mar, Colares, Portugal"
                },
                "date": "2019",
                "gear": "Sony A7 + FE 28-70 mm F3.5-5.6 OSS"
            }
        },
        "o-bliss": {
            "title": "O bonheur!",
            "text": {
                "quote_1": "Glorieux, spectacle émouvant! La poésie du mouvement! La vraie façon de voyager! La seule façon de voyager! Ici aujourd'hui - dans la semaine prochaine demain! Les villages ont sauté, les villes ont sauté - toujours l'horizon de quelqu'un d'autre! O bonheur! O merde! merde! O mon! O mon!",
                "quote_1_author": "Kenneth Grahame, Le Vent dans les Saules"
            },
            "details": {
                "location": {
                    "url": "https://www.google.fr/maps/place/Dune+du+Pilat",
                    "value": "Dune du Pilat, France"
                },
                "date": "2019",
                "gear": "Sony A7 + FE 28-70 mm F3.5-5.6 OSS"
            }
        },
        "alfacinhas-on-foot": {
            "title": "Alfacinhas à pied",
            "text": {
                "line_1": "Alfacinhas ou petites laitues est un terme qui désigne familièrement les habitants de Lisbonne.",
                "line_2": "Ce terme a été popularisé par Almeida Garrett dans son livre Viagens na Minha Terra, dans lequel il fait référence, à un moment donné,",
                "quote_1": "Parce que vous resteront alfacinhas pour toujours, en veillant à ce que toutes les places de ce monde soient comme celles du Terreiro do Paço.",
                "line_3": "L'auteur a fini par ne pas expliquer le pourquoi, alors la vérité est que cette nourriture a donné son nom aux habitants de Lisbonne et personne ne sait pourquoi.",
                "line_4": "Lors d'un week-end bien passé dans la magnifique capitale Portugaise, j'ai eu l'occasion de capturer ses habitants à travers mon objectif, toujours dans une perspective intéressante et, surtout, avec une composition équilibrée."
            },
            "details": {
                "location": {
                    "url": "https://www.google.fr/maps/place/Lisbonne",
                    "value": "Lisbonne, Portugal"
                },
                "date": "2021",
                "gear": "Fujifilm X-T3 + XF 35mm f/2 R WR"
            }
        },
        "where-sea-is-bluest": {
            "title": "Où la Mer est la Plus Bleue",
            "text": {
                "quote_1_1": "Ericeira, Là où la Mer est la Plus Bleue",
                "quote_1_1_translation_source": "Ericeira, Onde o Mar é Mais Azul",
                "quote_1_2": "Sur les belles plages du sud",
                "quote_1_2_translation_source": "Nas belas praias do sul",
                "quote_1_3": "De doré et frais sable",
                "quote_1_3_translation_source": "De doirada e fresca areia",
                "quote_1_author": "Gabriel Cardoso, Ericeira"
            },
            "details": {
                "location": {
                    "url": "https://www.google.fr/maps/place/Ericeira",
                    "value": "Ericeira, Portugal"
                },
                "date": "2021",
                "gear": "Fujifilm X-T3 + XF 35mm f/2 R WR"
            }
        },
        "all-beginnings-are-involuntary": {
            "title": "Tout début est involontaire",
            "text": {
                "quote_1_1": "Tout début est involontaire.",
                "quote_1_1_translation_source": "Todo começo é involuntário.",
                "quote_1_2": "Dieu est l'agent.",
                "quote_1_2_translation_source": "Deus é o agente.",
                "quote_1_3": "Le héros se regarde, confus",
                "quote_1_3_translation_source": "O herói a si assiste, vário",
                "quote_1_4": "Et inconscient.",
                "quote_1_4_translation_source": "E inconsciente.",
                "quote_1_author": "Fernando Pessoa, Mensagem"
            },
            "details": {
                "location": {
                    "url": "https://www.google.fr/maps/place/Lisbonne",
                    "value": "Lisbonne, Portugal"
                },
                "date": "2021",
                "gear": "Fujifilm X-T3 + XF 35mm f/2 R WR"
            }
        },
        "coimbra-old-town": {
            "title": "Vieille ville de Coimbra",
            "details": {
                "location": {
                    "url": "https://www.google.fr/maps/place/Coimbra",
                    "value": "Coimbra, Portugal"
                },
                "date": "2021",
                "gear": "Fujifilm X-T3 + XF 35mm f/2 R WR"
            }
        }
    },

    "explore": {
        "categories": {
            "nature": "Nature",
            "street": "Rue",
            "sea": "Mer",
            "people": "Gens"
        }
    }
}